{"id":"23639575","name":"Jowett Close","nodes":[{"type":"node","id":256098907,"lat":52.3898141,"lon":-0.692409,"tags":{"created_by":"JOSM"}},{"type":"node","id":256098908,"lat":52.3896833,"lon":-0.6923872,"tags":{"created_by":"JOSM"}},{"type":"node","id":256098909,"lat":52.3895316,"lon":-0.692276},{"type":"node","id":256098910,"lat":52.3894545,"lon":-0.6921801,"tags":{"created_by":"JOSM"}},{"type":"node","id":256098912,"lat":52.3892856,"lon":-0.6920385,"tags":{"created_by":"JOSM"}},{"type":"node","id":256098913,"lat":52.3890841,"lon":-0.6919622,"tags":{"created_by":"JOSM"}}],"volunteer_postcode":"NN15 5UF"}