{"id":"24329472","name":"Gracechurch Court","nodes":[{"type":"node","id":263895148,"lat":52.5880901,"lon":-0.2235184,"tags":{"created_by":"JOSM"}},{"type":"node","id":263895150,"lat":52.588166,"lon":-0.22367,"tags":{"created_by":"JOSM"}},{"type":"node","id":263895152,"lat":52.5881821,"lon":-0.2237142,"tags":{"created_by":"JOSM"}},{"type":"node","id":263895153,"lat":52.5881821,"lon":-0.223776,"tags":{"created_by":"JOSM"}},{"type":"node","id":263895155,"lat":52.5881445,"lon":-0.2239762,"tags":{"created_by":"JOSM"}},{"type":"node","id":263895156,"lat":52.5881428,"lon":-0.2240498,"tags":{"created_by":"JOSM"}},{"type":"node","id":263895157,"lat":52.5881624,"lon":-0.2241028,"tags":{"created_by":"JOSM"}},{"type":"node","id":263895159,"lat":52.5881946,"lon":-0.2241175,"tags":{"created_by":"JOSM"}},{"type":"node","id":263895160,"lat":52.5882322,"lon":-0.2241057,"tags":{"created_by":"JOSM"}},{"type":"node","id":263895161,"lat":52.5882644,"lon":-0.2240586,"tags":{"created_by":"JOSM"}}]}