{"id":"24416406","name":"Kendal Close","nodes":[{"type":"node","id":265089472,"lat":52.6105147,"lon":-0.2452027},{"type":"node","id":265089496,"lat":52.6102994,"lon":-0.2452778},{"type":"node","id":265089497,"lat":52.6101234,"lon":-0.245192,"tags":{"created_by":"JOSM"}},{"type":"node","id":265089498,"lat":52.6100017,"lon":-0.2451009,"tags":{"created_by":"JOSM"}},{"type":"node","id":265089499,"lat":52.6099354,"lon":-0.2449551,"tags":{"created_by":"JOSM"}},{"type":"node","id":265089500,"lat":52.6099249,"lon":-0.2446786,"tags":{"created_by":"JOSM"}},{"type":"node","id":265089501,"lat":52.6099775,"lon":-0.2444545,"tags":{"created_by":"JOSM"}},{"type":"node","id":265388178,"lat":52.6100166,"lon":-0.2443088,"tags":{"created_by":"JOSM"}},{"type":"node","id":265388185,"lat":52.6099321,"lon":-0.2448668,"tags":{"created_by":"JOSM"}},{"type":"node","id":2383085488,"lat":52.6104593,"lon":-0.2452278,"tags":{"bicycle":"yes","crossing":"unmarked","highway":"crossing","kerb":"lowered","source":"survey"}}]}