{"id":"4244287","name":"Beech Drive","nodes":[{"type":"node","id":25371750,"lat":52.0418639,"lon":-1.148094,"tags":{"created_by":"JOSM"}},{"type":"node","id":25371756,"lat":52.0418614,"lon":-1.1481983,"tags":{"created_by":"JOSM"}},{"type":"node","id":25372966,"lat":52.0416487,"lon":-1.1493356,"tags":{"created_by":"JOSM"}},{"type":"node","id":25373045,"lat":52.041735,"lon":-1.1491267,"tags":{"created_by":"JOSM"}},{"type":"node","id":25373048,"lat":52.0417693,"lon":-1.1490638,"tags":{"created_by":"JOSM"}},{"type":"node","id":25373050,"lat":52.0418371,"lon":-1.1489652,"tags":{"created_by":"JOSM"}},{"type":"node","id":25373053,"lat":52.0418591,"lon":-1.148916,"tags":{"created_by":"JOSM"}},{"type":"node","id":25373054,"lat":52.041867,"lon":-1.1488531,"tags":{"created_by":"JOSM"}},{"type":"node","id":25373055,"lat":52.0418612,"lon":-1.1488075,"tags":{"created_by":"JOSM"}},{"type":"node","id":25373056,"lat":52.041836,"lon":-1.1486988,"tags":{"created_by":"JOSM"}},{"type":"node","id":25373058,"lat":52.0418298,"lon":-1.1486416,"tags":{"created_by":"JOSM"}},{"type":"node","id":25373060,"lat":52.0418301,"lon":-1.1485722,"tags":{"created_by":"JOSM"}},{"type":"node","id":25373061,"lat":52.0418375,"lon":-1.1485293,"tags":{"created_by":"JOSM"}},{"type":"node","id":25373062,"lat":52.0418662,"lon":-1.1484334,"tags":{"created_by":"JOSM"}},{"type":"node","id":25373063,"lat":52.0418799,"lon":-1.148382,"tags":{"created_by":"JOSM"}},{"type":"node","id":25373064,"lat":52.0418828,"lon":-1.1483457,"tags":{"created_by":"JOSM"}},{"type":"node","id":25373065,"lat":52.0418821,"lon":-1.1483013,"tags":{"created_by":"JOSM"}},{"type":"node","id":25373066,"lat":52.041877,"lon":-1.1482557,"tags":{"created_by":"JOSM"}}]}