{"id":"4854561","name":"Hillside Avenue","nodes":[{"type":"node","id":31300938,"lat":52.093831,"lon":-1.0223367,"tags":{"created_by":"JOSM"}},{"type":"node","id":31300942,"lat":52.0931537,"lon":-1.0226779,"tags":{"created_by":"JOSM"}},{"type":"node","id":31300944,"lat":52.0926135,"lon":-1.022796,"tags":{"created_by":"JOSM"}},{"type":"node","id":31300946,"lat":52.0924506,"lon":-1.0227721,"tags":{"created_by":"JOSM"}},{"type":"node","id":31300947,"lat":52.0928798,"lon":-1.0227667,"tags":{"created_by":"JOSM"}}]}