{"lat":"-1.026887","lng":"52.142152","postcode":"NN12 8AY","streets":[{"id":"191667993","name":"School Lane","distance":184},{"id":"3369237","name":"Smithland Court","distance":105},{"id":"3369240","name":"Bradden Way","distance":83},{"id":"3369247","name":"Windmill Way","distance":125},{"id":"3369249","name":"Bengal","distance":411},{"id":"3369250","name":"Bengal","distance":513},{"id":"3369557","name":"New Road","distance":169},{"id":"3373752","name":"Home Close","distance":72},{"id":"3373755","name":"Mansfield Court","distance":128},{"id":"4618461","name":"Windmill Way","distance":125},{"id":"4618462","name":"Windmill Way","distance":105},{"id":"4618492","name":"New Road","distance":138},{"id":"4618493","name":"New Road","distance":156},{"id":"4618494","name":"New Road","distance":138},{"id":"4618495","name":"New Road","distance":125},{"id":"4618497","name":"Smithland Court","distance":186},{"id":"4618498","name":"Smithland Court","distance":262},{"id":"4618499","name":"Smithland Court","distance":202},{"id":"4618500","name":"Home Close","distance":20},{"id":"4618501","name":"Home Close","distance":28},{"id":"4618502","name":"Home Close","distance":69},{"id":"4618510","name":"Home Close","distance":19},{"id":"4618511","name":"Home Close","distance":47},{"id":"4618514","name":"Bengal","distance":484},{"id":"8127899","name":"Mansfield Court","distance":128}]}