{"lat":"-0.670012","lng":"52.370166","postcode":"NN15 5TS","streets":[{"id":"314253034","name":"Spinney Road","distance":128},{"id":"319573480","name":"Sycamore Gardens","distance":193},{"id":"455395606","name":"Slipton Road","distance":279},{"id":"455395608","name":"Twywell Way","distance":198},{"id":"455395609","name":"Barnwell Close","distance":15},{"id":"455395610","name":"Woodford Road","distance":128},{"id":"455395611","name":"Lowick Close","distance":179},{"id":"455395612","name":"Twywell Way","distance":215},{"id":"455395613","name":"Aldwinckle Road","distance":102},{"id":"455395614","name":"Barnwell Close","distance":44},{"id":"503044458","name":"Denford Close","distance":102},{"id":"689191911","name":"The Green","distance":3351},{"id":"96314995","name":"George Street","distance":267},{"id":"96314996","name":"Bird Street","distance":246},{"id":"96314998","name":"Woodcock Street","distance":334},{"id":"96314999","name":"Coppice Close","distance":275},{"id":"96315001","name":"Spinney Road","distance":75},{"id":"96315006","name":"Poplar Road","distance":271},{"id":"96315007","name":"Elm Road","distance":348},{"id":"96315008","name":"Forest Close","distance":211},{"id":"96747391","name":"St Andrew's Lane","distance":3104},{"id":"96747392","name":"St Andrew's Lane","distance":3088},{"id":"96747395","name":"St Andrew's Lane","distance":3065},{"id":"96747396","name":"Top Dysons","distance":2740},{"id":"96747885","name":"Butchers Paddock","distance":3128},{"id":"96749225","name":"The Green","distance":3253},{"id":"96749341","name":"Battle Close","distance":3103},{"id":"96755264","name":"Acorn Park","distance":135}]}