{"lat":"-0.685823","lng":"52.36253","postcode":"NN15 5QY","streets":[{"id":"92303586","name":"Severn Court","distance":148},{"id":"92309214","name":"Nene Road","distance":100},{"id":"92309223","name":"Glebe Road","distance":309},{"id":"92309225","name":"Park Road","distance":30},{"id":"92309229","name":"Charles Court","distance":152},{"id":"92309232","name":"Regent Road","distance":225},{"id":"92309246","name":"Shakespeare Drive","distance":227},{"id":"92309846","name":"Thames Court","distance":172}]}