{"lat":"-0.720822","lng":"52.40464","postcode":"NN16 8RR","streets":[{"id":"24329807","name":"King Street"},{"id":"24329808","name":"Nelson Street"},{"id":"24329810","name":"Princes Street"},{"id":"24451232","name":"Tresham Street"},{"id":"24451234","name":"Lindsay Street"},{"id":"24451236","name":"Club Street"},{"id":"24451271","name":"Digby Street"},{"id":"24451362","name":"Catesby Street"},{"id":"24451363","name":"Scotland Street"},{"id":"24451364","name":"Weldon Street"},{"id":"24451910","name":"Lancaster Road"},{"id":"565140672","name":"Princes Street"},{"id":"565140673","name":"Tresham Street"},{"id":"565140674","name":"Scotland Street"},{"id":"92213055","name":"Vermont Standing"},{"id":"92213063","name":"Bonham Court"},{"id":"92213079","name":"Bath Lane"}]}