{"lat":"-0.706041","lng":"52.480234","postcode":"NN18 9ND","streets":[{"id":"56435106","name":"Thomas Close"},{"id":"56435116","name":"Patrick Road"},{"id":"56472858","name":"Bewick Court"},{"id":"56472859","name":"Bell Court"},{"id":"97824724","name":"Birch Avenue"},{"id":"97824778","name":"Hunt Street"},{"id":"98099115","name":"Sargent Road"},{"id":"98099173","name":"Sandby Road"},{"id":"98099211","name":"Sargent Road"},{"id":"98099250","name":"Sandby Road"},{"id":"98125230","name":"Stokes Road"}]}