{"lat":"-0.878253","lng":"52.213277","postcode":"NN4 7BU","streets":[{"id":"105411700","name":"Coneygree","distance":237},{"id":"192024817","name":"Firs Court","distance":63},{"id":"30424314","name":"Back Lane","distance":191},{"id":"494395547","name":"Pavilion Drive","distance":511},{"id":"52571384","name":"Pavilion Drive","distance":500},{"id":"54478602","name":"Bouverie Road","distance":211},{"id":"54478777","name":"Windrush Road","distance":179},{"id":"54483145","name":"Houghton Hill","distance":210},{"id":"54484239","name":"Ilex close","distance":204}]}