{"lat":"-0.920388","lng":"52.224867","postcode":"NN4 8RZ","streets":[{"id":"101271033","name":"Rydalside","distance":238},{"id":"101271035","name":"Rydalside","distance":248},{"id":"101271045","name":"Piccadilly Close","distance":98},{"id":"101271051","name":"Southwood Hill","distance":220},{"id":"101810506","name":"Five Acres Fold","distance":355},{"id":"101810532","name":"Five Acres Fold","distance":327},{"id":"101810533","name":"Five Acres Fold","distance":316},{"id":"105411687","name":"Rotherhithe Close","distance":364},{"id":"69260943","name":"Hunsbarrow Road","distance":137},{"id":"72855001","name":"Dayrell Road","distance":394},{"id":"74891895","name":"Benjamin Square","distance":344},{"id":"74892047","name":"Plantagenet Square","distance":288},{"id":"74892055","name":"Plantagenet Square","distance":308},{"id":"74892318","name":"Joshua Square","distance":332},{"id":"74892341","name":"Yarwell Square","distance":275},{"id":"82783079","name":"Floribunda Drive","distance":29},{"id":"82785200","name":"Piccadilly Close","distance":137},{"id":"99067386","name":"Jublee Close","distance":94},{"id":"99067388","name":"Brocade Close","distance":141},{"id":"99067389","name":"Piccadilly Close","distance":189},{"id":"99067391","name":"Piccadilly Close","distance":171},{"id":"99067393","name":"Peace Close","distance":41},{"id":"99067394","name":"Jubilee Close","distance":32},{"id":"99067396","name":"Floribunda Drive","distance":131},{"id":"99067397","name":"Floribunda Drive","distance":165},{"id":"99067399","name":"Rosenella Close","distance":26},{"id":"99067400","name":"Dickson Close","distance":58},{"id":"99067401","name":"Floribunda Drive","distance":153},{"id":"99067402","name":"Peace Close","distance":83}]}