{"lat":"-0.951422","lng":"52.239961","postcode":"NN5 4DZ","streets":[{"id":"117080152","name":"Kent Road","distance":198},{"id":"170452924","name":"Brown Close","distance":292},{"id":"170452926","name":"Dave Bowen Close","distance":198},{"id":"170452927","name":"Dave Bowen Close","distance":268},{"id":"170452930","name":"Jack English Close","distance":371},{"id":"170452931","name":"Jack Parnell Close","distance":285},{"id":"170452932","name":"Milburn Drive","distance":142},{"id":"170452933","name":"Milburn Drive","distance":162},{"id":"170452934","name":"Milburn Drive","distance":341},{"id":"170452946","name":"Thompson Close","distance":377},{"id":"170452948","name":"Thompson Close","distance":371},{"id":"244084115","name":"Jack English Close","distance":402},{"id":"459079237","name":"Eden Road","distance":150},{"id":"459079238","name":"Howarth Way","distance":56},{"id":"459079239","name":"Eden Way","distance":118},{"id":"459079240","name":"Scott Close","distance":18},{"id":"647882572","name":"Hardy Close","distance":107}]}