{"lat":"-0.951422","lng":"52.239961","postcode":"NN5 4DZ","streets":[{"id":"117080152","name":"Kent Road"},{"id":"170452924","name":"Brown Close"},{"id":"170452926","name":"Dave Bowen Close"},{"id":"170452927","name":"Dave Bowen Close"},{"id":"170452930","name":"Jack English Close"},{"id":"170452931","name":"Jack Parnell Close"},{"id":"170452932","name":"Milburn Drive"},{"id":"170452933","name":"Milburn Drive"},{"id":"170452934","name":"Milburn Drive"},{"id":"170452946","name":"Thompson Close"},{"id":"170452948","name":"Thompson Close"},{"id":"244084115","name":"Jack English Close"},{"id":"459079237","name":"Eden Road"},{"id":"459079238","name":"Howarth Way"},{"id":"459079239","name":"Eden Way"},{"id":"459079240","name":"Scott Close"},{"id":"647882572","name":"Hardy Close"}]}