{"id":"24451912","name":"Edinburgh Road","nodes":[{"type":"node","id":265757415,"lat":52.4050942,"lon":-0.715505,"tags":{"created_by":"JOSM"}},{"type":"node","id":265757463,"lat":52.4050222,"lon":-0.7153089,"tags":{"created_by":"JOSM"}},{"type":"node","id":265757465,"lat":52.404944,"lon":-0.7150499,"tags":{"created_by":"JOSM"}},{"type":"node","id":265757468,"lat":52.4048414,"lon":-0.7147128,"tags":{"created_by":"JOSM"}},{"type":"node","id":265757469,"lat":52.4047095,"lon":-0.7143415,"tags":{"created_by":"JOSM"}},{"type":"node","id":265757470,"lat":52.4046264,"lon":-0.714063,"tags":{"created_by":"JOSM"}},{"type":"node","id":265757471,"lat":52.4045434,"lon":-0.713809,"tags":{"created_by":"JOSM"}},{"type":"node","id":265757472,"lat":52.4044408,"lon":-0.7135354,"tags":{"created_by":"JOSM"}},{"type":"node","id":265757473,"lat":52.4042942,"lon":-0.7133399,"tags":{"created_by":"JOSM"}},{"type":"node","id":265757474,"lat":52.4041574,"lon":-0.7131787,"tags":{"created_by":"JOSM"}},{"type":"node","id":265757475,"lat":52.4040255,"lon":-0.7130126,"tags":{"created_by":"JOSM"}},{"type":"node","id":265757476,"lat":52.4039082,"lon":-0.712866,"tags":{"created_by":"JOSM"}},{"type":"node","id":265757477,"lat":52.4038504,"lon":-0.7127664}],"volunteer_postcode":"NN16 0RA","closest_distance":144}