{"id":"31191729","name":"Topwell Court","nodes":[{"type":"node","id":347026731,"lat":52.2520616,"lon":-0.8289099},{"type":"node","id":347068975,"lat":52.2520009,"lon":-0.8289548},{"type":"node","id":347068977,"lat":52.2519557,"lon":-0.8290032},{"type":"node","id":347068978,"lat":52.2519062,"lon":-0.8291176},{"type":"node","id":347068980,"lat":52.2518973,"lon":-0.8292672},{"type":"node","id":347068982,"lat":52.2519331,"lon":-0.8293907},{"type":"node","id":347068984,"lat":52.2520135,"lon":-0.8294339},{"type":"node","id":347068986,"lat":52.252074,"lon":-0.8294358},{"type":"node","id":347068988,"lat":52.2521836,"lon":-0.8293749},{"type":"node","id":360894950,"lat":52.2519639,"lon":-0.8294185,"tags":{"created_by":"JOSM"}},{"type":"node","id":360894955,"lat":52.2519083,"lon":-0.8293444,"tags":{"created_by":"JOSM"}},{"type":"node","id":360894959,"lat":52.2518985,"lon":-0.8291847,"tags":{"created_by":"JOSM"}},{"type":"node","id":360894964,"lat":52.2519249,"lon":-0.8290571,"tags":{"created_by":"JOSM"}},{"type":"node","id":360894972,"lat":52.2521226,"lon":-0.8294141,"tags":{"created_by":"JOSM"}},{"type":"node","id":1323308769,"lat":52.2519459,"lon":-0.8290203}],"volunteer_postcode":"NN3 9HN","closest_distance":435}