{"id":"4232959","name":"Gayton Road","nodes":[{"type":"node","id":14906950,"lat":52.180721,"lon":-1.007029,"tags":{"created_by":"JOSM"}},{"type":"node","id":25259840,"lat":52.1805776,"lon":-1.0070022,"tags":{"created_by":"JOSM"}},{"type":"node","id":25259841,"lat":52.1802247,"lon":-1.0069703,"tags":{"created_by":"JOSM"}},{"type":"node","id":25259842,"lat":52.1798286,"lon":-1.006931,"tags":{"created_by":"JOSM"}},{"type":"node","id":25259843,"lat":52.1796372,"lon":-1.006897,"tags":{"created_by":"JOSM"}},{"type":"node","id":25259846,"lat":52.1792388,"lon":-1.0067514},{"type":"node","id":25259848,"lat":52.1790784,"lon":-1.0066057,"tags":{"created_by":"JOSM"}},{"type":"node","id":25259855,"lat":52.1785717,"lon":-1.0060271,"tags":{"created_by":"JOSM"}},{"type":"node","id":25259856,"lat":52.1784584,"lon":-1.0059033,"tags":{"created_by":"JOSM"}},{"type":"node","id":25259857,"lat":52.1783807,"lon":-1.0058234,"tags":{"created_by":"JOSM"}},{"type":"node","id":25259858,"lat":52.1782827,"lon":-1.0057181,"tags":{"created_by":"JOSM"}},{"type":"node","id":25259859,"lat":52.1782182,"lon":-1.0056527,"tags":{"created_by":"JOSM"}},{"type":"node","id":25259860,"lat":52.1781358,"lon":-1.0055692,"tags":{"created_by":"JOSM"}},{"type":"node","id":25259861,"lat":52.1779955,"lon":-1.005424,"tags":{"created_by":"JOSM"}},{"type":"node","id":25259862,"lat":52.1779621,"lon":-1.0053804,"tags":{"created_by":"JOSM"}},{"type":"node","id":25259863,"lat":52.1779376,"lon":-1.0053332,"tags":{"created_by":"JOSM"}},{"type":"node","id":25259864,"lat":52.1779064,"lon":-1.0052497,"tags":{"created_by":"JOSM"}},{"type":"node","id":25259865,"lat":52.1778641,"lon":-1.0051408,"tags":{"created_by":"JOSM"}},{"type":"node","id":25259866,"lat":52.1777704,"lon":-1.0048212,"tags":{"created_by":"JOSM"}},{"type":"node","id":25259867,"lat":52.1777282,"lon":-1.0046537,"tags":{"created_by":"JOSM"}},{"type":"node","id":25259868,"lat":52.1776078,"lon":-1.0041096,"tags":{"created_by":"JOSM"}},{"type":"node","id":25259869,"lat":52.1775257,"lon":-1.0037719,"tags":{"created_by":"JOSM"}},{"type":"node","id":25281121,"lat":52.1795805,"lon":-1.0068818,"tags":{"created_by":"JOSM"}},{"type":"node","id":25281129,"lat":52.1789529,"lon":-1.0064803,"tags":{"created_by":"JOSM"}},{"type":"node","id":25281130,"lat":52.1788311,"lon":-1.0063403,"tags":{"created_by":"JOSM"}},{"type":"node","id":25281131,"lat":52.1786967,"lon":-1.0061705,"tags":{"created_by":"JOSM"}},{"type":"node","id":25281957,"lat":52.1777859,"lon":-1.0048899,"tags":{"created_by":"JOSM"}},{"type":"node","id":25282397,"lat":52.1794047,"lon":-1.0068447},{"type":"node","id":25282451,"lat":52.1788879,"lon":-1.0064124,"tags":{"created_by":"JOSM"}},{"type":"node","id":25282478,"lat":52.1778874,"lon":-1.0052117,"tags":{"created_by":"JOSM"}},{"type":"node","id":25282479,"lat":52.1774124,"lon":-1.0035155}],"volunteer_postcode":"NN12 8LT","closest_distance":1225}