{"id":"4367138","name":"Mill Close","nodes":[{"type":"node","id":26612800,"lat":52.2923861,"lon":-1.2129606,"tags":{"created_by":"JOSM"}},{"type":"node","id":26616788,"lat":52.292037,"lon":-1.2145391,"tags":{"created_by":"JOSM"}},{"type":"node","id":26616789,"lat":52.2923272,"lon":-1.213856,"tags":{"created_by":"JOSM"}},{"type":"node","id":26616790,"lat":52.2923777,"lon":-1.2136945,"tags":{"created_by":"JOSM"}},{"type":"node","id":26616791,"lat":52.2923997,"lon":-1.2135582,"tags":{"created_by":"JOSM"}},{"type":"node","id":26616792,"lat":52.2924084,"lon":-1.2134039,"tags":{"created_by":"JOSM"}},{"type":"node","id":26616793,"lat":52.2924084,"lon":-1.2132101,"tags":{"created_by":"JOSM"}},{"type":"node","id":26617386,"lat":52.2921038,"lon":-1.2144225,"tags":{"created_by":"JOSM"}}],"volunteer_postcode":"NN11 7JN"}