{"id":"4618494","name":"New Road","nodes":[{"type":"node","id":15242354,"lat":52.1433608,"lon":-1.0265611},{"type":"node","id":15242355,"lat":52.1433232,"lon":-1.0264754},{"type":"node","id":15242367,"lat":52.1433302,"lon":-1.0264811},{"type":"node","id":15242369,"lat":52.1433468,"lon":-1.0265071},{"type":"node","id":15242371,"lat":52.1433365,"lon":-1.0264887},{"type":"node","id":15242378,"lat":52.1433415,"lon":-1.026496},{"type":"node","id":15242386,"lat":52.1433524,"lon":-1.0265251}],"volunteer_postcode":"NN12 8AY","closest_distance":138}