{"id":"4620154","name":"Shepherds Walk","nodes":[{"type":"node","id":28253506,"lat":52.2401178,"lon":-0.9856547,"tags":{"created_by":"JOSM"}},{"type":"node","id":28297505,"lat":52.2400767,"lon":-0.9853016,"tags":{"created_by":"JOSM"}},{"type":"node","id":28297507,"lat":52.2400487,"lon":-0.985169,"tags":{"created_by":"JOSM"}},{"type":"node","id":28297508,"lat":52.2400221,"lon":-0.9850938,"tags":{"created_by":"JOSM"}},{"type":"node","id":28297509,"lat":52.2399927,"lon":-0.9850413,"tags":{"created_by":"JOSM"}},{"type":"node","id":28297511,"lat":52.2399293,"lon":-0.9849883,"tags":{"created_by":"JOSM"}},{"type":"node","id":28297512,"lat":52.2398862,"lon":-0.9849677,"tags":{"created_by":"JOSM"}},{"type":"node","id":28297513,"lat":52.2398218,"lon":-0.9849585,"tags":{"created_by":"JOSM"}},{"type":"node","id":28297515,"lat":52.2399647,"lon":-0.9850113,"tags":{"created_by":"JOSM"}},{"type":"node","id":29335505,"lat":52.2397168,"lon":-0.9849578,"tags":{"barrier":"gate","created_by":"JOSM"}}],"volunteer_postcode":"NN5 4AR","closest_distance":2530}