{"id":"8684114","name":"The Orchard","nodes":[{"type":"node","id":62037697,"lat":52.0838084,"lon":-0.90034,"tags":{"created_by":"JOSM"}},{"type":"node","id":62037703,"lat":52.083447,"lon":-0.9017546},{"type":"node","id":62037709,"lat":52.0837015,"lon":-0.9012143,"tags":{"created_by":"JOSM"}},{"type":"node","id":62037713,"lat":52.0837509,"lon":-0.9010397,"tags":{"created_by":"JOSM"}},{"type":"node","id":62037717,"lat":52.0837813,"lon":-0.9007958,"tags":{"created_by":"JOSM"}}],"volunteer_postcode":"MK19 6GN","closest_distance":3670}