{"id":"96831848","name":"House Martin Close","nodes":[{"type":"node","id":1121969991,"lat":52.4453592,"lon":-0.8119687},{"type":"node","id":1121970061,"lat":52.4457768,"lon":-0.8125807},{"type":"node","id":1121970089,"lat":52.4458095,"lon":-0.8127524},{"type":"node","id":1121970254,"lat":52.4456917,"lon":-0.8124198},{"type":"node","id":1121970301,"lat":52.4455348,"lon":-0.8122696},{"type":"node","id":2610213768,"lat":52.4453397,"lon":-0.8120532}],"volunteer_postcode":"NN14 2GL","closest_distance":136}