{"lat":"-0.720024","lng":"52.489071","postcode":"NN18 0EZ","streets":[{"id":"56435112","name":"Newark Drive"},{"id":"56467509","name":"Oxford road"},{"id":"56467511","name":"Dorset Road"},{"id":"56467512","name":"Surrey Close"},{"id":"56471731","name":"Clumber Court"},{"id":"56471885","name":"Cornwall Close"},{"id":"56471895","name":"Warwick Way"},{"id":"98099121","name":"Gunthorpe Place"},{"id":"98099128","name":"Weston Walk"},{"id":"98099147","name":"Birdgford Place"},{"id":"98099183","name":"Carlton Place"},{"id":"98099213","name":"Granby Close"},{"id":"98099235","name":"Birdgford Place"},{"id":"98099244","name":"Barton Square"},{"id":"98099256","name":"Gateford Court"}]}